hass_frontend/__init__.py
hass_frontend/authorize.html
hass_frontend/index.html
hass_frontend/onboarding.html
hass_frontend/py.typed
hass_frontend/robots.txt
hass_frontend/service_worker.js
hass_frontend/frontend_latest/_src_util_recorder_worklet_js.js
hass_frontend/frontend_latest/app.js
hass_frontend/frontend_latest/authorize.js
hass_frontend/frontend_latest/build_mdi_iconList_json.js
hass_frontend/frontend_latest/core.js
hass_frontend/frontend_latest/custom-panel.js
hass_frontend/frontend_latest/hassio_src_dialogs_backup_dialog-hassio-backup_ts-node_modules_polymer_font-roboto_roboto_js--62e845.js
hass_frontend/frontend_latest/hassio_src_hassio-my-redirect_ts.js
hass_frontend/frontend_latest/manifest.json
hass_frontend/frontend_latest/markdown-worker.js
hass_frontend/frontend_latest/node_modules_date-fns_esm_isFirstDayOfMonth_index_js-src_panels_energy_strategies_energy-view-b589a8.js
hass_frontend/frontend_latest/node_modules_date-fns_esm_isFirstDayOfMonth_index_js-src_panels_lovelace_cards_energy_hui-ene-0ec7bd.js
hass_frontend/frontend_latest/node_modules_date-fns_esm_isFirstDayOfMonth_index_js-src_panels_lovelace_cards_energy_hui-ene-1dfa10.js
hass_frontend/frontend_latest/node_modules_date-fns_esm_isFirstDayOfMonth_index_js-src_panels_lovelace_cards_energy_hui-ene-8782ce.js
hass_frontend/frontend_latest/node_modules_date-fns_esm_isFirstDayOfMonth_index_js-src_panels_lovelace_cards_energy_hui-ene-8d6927.js
hass_frontend/frontend_latest/node_modules_date-fns_esm_isFirstDayOfMonth_index_js-src_panels_lovelace_cards_energy_hui-ene-b19639.js
hass_frontend/frontend_latest/node_modules_date-fns_esm_isFirstDayOfMonth_index_js-src_panels_lovelace_cards_energy_hui-ene-ed1d8b.js
hass_frontend/frontend_latest/node_modules_date-fns_esm_isFirstDayOfMonth_index_js-src_panels_lovelace_cards_energy_hui-ene-fbcbd5.js
hass_frontend/frontend_latest/node_modules_date-fns_esm_isFirstDayOfMonth_index_js-src_panels_lovelace_strategies_original--5e5449.js
yoreek_home_assistant_frontend-20231228.1.dist-info/LICENSE.md
yoreek_home_assistant_frontend-20231228.1.dist-info/METADATA
yoreek_home_assistant_frontend-20231228.1.dist-info/WHEEL
yoreek_home_assistant_frontend-20231228.1.dist-info/top_level.txt
yoreek_home_assistant_frontend-20231228.1.dist-info/RECORD
