Metadata-Version: 2.1
Name: yoreek-home-assistant-frontend
Version: 20231228.1
Summary: The Home Assistant frontend
Author-email: The Home Assistant Authors <hello@home-assistant.io>
License: Apache-2.0
Project-URL: Homepage, https://github.com/home-assistant/frontend
Platform: any
Requires-Python: >=3.10.0
License-File: LICENSE.md
